ai_sdk/__init__.py
ai_sdk/anthropic/__init__.py
ai_sdk/anthropic/chat_model.py
ai_sdk/anthropic/provider.py
ai_sdk/core/__init__.py
ai_sdk/core/convert_response.py
ai_sdk/core/errors.py
ai_sdk/core/generate_object.py
ai_sdk/core/generate_text.py
ai_sdk/core/language_model.py
ai_sdk/core/retry_strategy.py
ai_sdk/core/tool_calls.py
ai_sdk/core/types.py
ai_sdk/core/utils.py
ai_sdk/openai/__init__.py
ai_sdk/openai/chat_model.py
ai_sdk/openai/provider.py
ai_sdk/openrouter/__init__.py
ai_sdk/openrouter/chat_model.py
ai_sdk/openrouter/provider.py
ai_sdk_py-0.1.11.dist-info/licenses/LICENSE
ai_sdk_py-0.1.11.dist-info/METADATA
ai_sdk_py-0.1.11.dist-info/WHEEL
ai_sdk_py-0.1.11.dist-info/top_level.txt
ai_sdk_py-0.1.11.dist-info/RECORD
