Metadata-Version: 2.4
Name: ai-sdk-py
Version: 0.1.11
Summary: A unified interface for working with different AI language model providers
Author-email: Jacques Verré <jverre@gmail.com>
License-Expression: MIT
Project-URL: Homepage, https://github.com/jverre/ai-sdk
Project-URL: Repository, https://github.com/jverre/ai-sdk
Keywords: ai,llm,openai,anthropic,genai,large language model
Requires-Python: >=3.9
License-File: LICENSE
Requires-Dist: dotenv
Requires-Dist: pydantic<3.0.0,>=2.10.6
Requires-Dist: httpx<0.29.0,>=0.28.1
Requires-Dist: validators<0.35.0,>=0.34.0
Requires-Dist: opik
Provides-Extra: test
Requires-Dist: pytest>=7.0.0; extra == "test"
Requires-Dist: pytest-cov>=4.0.0; extra == "test"
Requires-Dist: pytest-asyncio>=0.21.0; extra == "test"
Requires-Dist: pytest-repeat>=0.9.1; extra == "test"
Dynamic: license-file
